Workbook

Sheet Summary
A1: Zusammenfassung
A2: 2026-06-01
A3: Kennzahlen — formelbasiert.
A5: Gesamtinvestition | B5: =Assumptions!$B$4
A6: NPV (3-5 J.) | B6: =-Assumptions!$B$4+NPV(Assumptions!$B$9,Projections!E7:E9)
A7: IRR | B7: =IFERROR(IRR(Projections!E6:E9),0)
A8: Kumulierter Cashflow (Endjahr) | B8: =Projections!F9
A10: Kernaussage | B10: Neura sollte einen phasenweisen Markteintritt verfolgen, der sich zunächst auf hochkomplexe Dienstleistungssektoren (z. B. spezialisierte Pflege, Logistik-Hubs) konzentriert, wo die kognitive Adaptivität (AURA AI) zwingend erforderlich ist. Die größte strategische Herausforderung ist nicht die Markt

Sheet Assumptions
A1: Annahmen
A2: 2026-06-01
A3: NUR gelbe Zellen bearbeiten — alle anderen Tabs rechnen daraus neu.
A4: Einmalinvestition | B4: 2000000 | C4: EUR
A5: Umsatz Jahr 1 | B5: 1500000 | C5: EUR
A6: Umsatzwachstum p.a. | B6: 0.3 | C6: %
A7: OpEx Jahr 1 | B7: 900000 | C7: EUR
A8: OpEx-Wachstum p.a. | B8: 0.15 | C8: %
A9: Diskontsatz (NPV) | B9: 0.12 | C9: %
A11: Adressierbare Marktgröße (TAM) für kognitive Robotik in Japan | B11: 500000000 | C11: EUR
A12: Anteil des Marktes, der durch kognitive Robotik adressiert werden kann (Year 1) | B12: 0.01 | C12: Decimal
A13: Jährliche Kosten für lokale Compliance und Rechtsberatung (Initial) | B13: 300000 | C13: EUR

Sheet Projections
A1: Projektionen
A2: 2026-06-01
A3: Formelbasiert aus 'Annahmen'.
A5: Jahr | B5: Umsatz | C5: OpEx | D5: EBITDA | E5: Cashflow | F5: Kumulierter Cashflow
A6: 0 | B6: 0 | C6: 0 | D6: 0 | E6: =-Assumptions!$B$4 | F6: =E6
A7: 1 | B7: =Assumptions!$B$5 | C7: =Assumptions!$B$7 | D7: =B7-C7 | E7: =D7 | F7: =F6+E7
A8: 2 | B8: =B7*(1+Assumptions!$B$6) | C8: =C7*(1+Assumptions!$B$8) | D8: =B8-C8 | E8: =D8 | F8: =F7+E8
A9: 3 | B9: =B8*(1+Assumptions!$B$6) | C9: =C8*(1+Assumptions!$B$8) | D9: =B9-C9 | E9: =D9 | F9: =F8+E9

Sheet Scenarios
A1: Szenarien
A2: 2026-06-01
A3: Gelbe Multiplikatoren anpassen — NPV je Szenario rechnet neu.
A5: Szenario | B5: Umsatz-Faktor | C5: Kosten-Faktor | D5: NPV
A6: Base | B6: 1 | C6: 1 | D6: =-Assumptions!$B$4+NPV(Assumptions!$B$9,(Projections!B7:B9*$B$6)-(Projections!C7:C9*$C$6))
A7: Optimistisch | B7: 1.2 | C7: 0.9 | D7: =-Assumptions!$B$4+NPV(Assumptions!$B$9,(Projections!B7:B9*$B$7)-(Projections!C7:C9*$C$7))
A8: Pessimistisch | B8: 0.8 | C8: 1.15 | D8: =-Assumptions!$B$4+NPV(Assumptions!$B$9,(Projections!B7:B9*$B$8)-(Projections!C7:C9*$C$8))

Sheet Sources
A1: Quellen & Audit-Trail
A2: 2026-06-01
A3: Herkunft jeder Annahme.
A5: Annahme | B5: Wert | C5: Einheit | D5: Quelle | E5: Konfidenz
A6: Adressierbare Marktgröße (TAM) für kognitive Robotik in Japan | B6: 500000000 | C6: EUR | D6: Experten-Schätzung basierend auf dem Bedarf an Service-Robotik (Pflege/Logistik) | E6: Estimate
A7: Anteil des Marktes, der durch kognitive Robotik adressiert werden kann (Year 1) | B7: 0.01 | C7: Decimal | D7: Pilotprojekt-Schätzung | E7: Estimate
A8: Jährliche Kosten für lokale Compliance und Rechtsberatung (Initial) | B8: 300000 | C8: EUR | D8: Lokale Experten-Schätzung | E8: Estimate
